nyx_client/__init__.py
nyx_client/circles.py
nyx_client/cli/__main__.py
nyx_client/cli/common.py
nyx_client/cli/init_env.py
nyx_client/client.py
nyx_client/configuration.py
nyx_client/connection.py
nyx_client/data.py
nyx_client/ontology.py
nyx_client/property.py
nyx_client/utils.py
nyx_client-0.2.5.dist-info/METADATA
nyx_client-0.2.5.dist-info/WHEEL
nyx_client-0.2.5.dist-info/entry_points.txt
nyx_client-0.2.5.dist-info/RECORD
