Metadata-Version: 2.1
Name: nyx-client
Version: 0.2.5
Summary: Nyx Client offers a simple API for interacting with data in your Nyx network.
Home-page: https://www.get-nyx.io
Keywords: client,data,sdk,ai,exchange,nyx,rag,gen-ai,iotics
Author: Iotics
Author-email: info@iotics.com
Requires-Python: >=3.10,<4.0
Classifier: Development Status :: 4 - Beta
Classifier: Intended Audience :: Developers
Classifier: License :: OSI Approved :: Apache Software License
Classifier: Programming Language :: Python :: 3
Classifier: Programming Language :: Python :: 3.10
Classifier: Programming Language :: Python :: 3.11
Classifier: Programming Language :: Python :: 3.12
Classifier: Topic :: Internet
Classifier: Topic :: Internet :: WWW/HTTP
Classifier: Topic :: Scientific/Engineering
Classifier: Topic :: Scientific/Engineering :: Artificial Intelligence
Classifier: Topic :: Software Development :: Libraries
Classifier: Topic :: Software Development :: Libraries :: Python Modules
Requires-Dist: click (>=8.1.7,<9.0.0)
Requires-Dist: python-dotenv (>=1.0.1,<2.0.0)
Requires-Dist: requests-toolbelt (>=1.0.0,<2.0.0)
Project-URL: Chat, https://discord.gg/zS8pVHjqSf
Project-URL: Changes, https://github.com/Iotic-Labs/nyx-sdk/blob/main/CHANGELOG.md
Project-URL: Documentation, https://nyx-client.readthedocs.io/en/stable
Project-URL: Issue tracker, https://github.com/Iotic-Labs/nyx-sdk/issues
Project-URL: Repository, https://github.com/Iotic-Labs/nyx-sdk
